chatrender/__init__.py
chatrender/apps.py
chatrender/celery.py
chatrender/conf.py
chatrender/exceptions.py
chatrender/urls.py
chatrender/management/__init__.py
chatrender/management/commands/__init__.py
chatrender/management/commands/publish_slackchat.py
chatrender/static/chatrender/css/internal.css
chatrender/static/chatrender/css/main-confab.css
chatrender/static/chatrender/css/main-election.css
chatrender/static/chatrender/css/main-monday.css
chatrender/static/chatrender/css/main-video.css
chatrender/static/chatrender/js/main-confab.js
chatrender/static/chatrender/js/main-confab.js.map
chatrender/static/chatrender/js/main-election.js
chatrender/static/chatrender/js/main-election.js.map
chatrender/static/chatrender/js/main-monday.js
chatrender/static/chatrender/js/main-monday.js.map
chatrender/static/chatrender/js/main-video.js
chatrender/static/chatrender/js/main-video.js.map
chatrender/tasks/__init__.py
chatrender/tasks/publish.py
chatrender/templates/chatrender/channel_list.html
chatrender/templates/chatrender/chattype_list.html
chatrender/templates/chatrender/common/base.html
chatrender/templates/chatrender/common/parts/footer.html
chatrender/templates/chatrender/common/parts/header.html
chatrender/templates/chatrender/common/parts/ads/banner.html
chatrender/templates/chatrender/common/parts/ads/cube.html
chatrender/templates/chatrender/common/parts/ads/script.html
chatrender/templates/chatrender/confab/header.html
chatrender/templates/chatrender/confab/index.html
chatrender/templates/chatrender/confab/meta/icons.html
chatrender/templates/chatrender/confab/meta/social.html
chatrender/templates/chatrender/confab/meta/telium.html
chatrender/templates/chatrender/election/elex-footer.html
chatrender/templates/chatrender/election/footer.html
chatrender/templates/chatrender/election/header.html
chatrender/templates/chatrender/election/index.html
chatrender/templates/chatrender/election/nav.html
django_politico_slackchat_renderer-0.2.14.dist-info/DESCRIPTION.rst
django_politico_slackchat_renderer-0.2.14.dist-info/METADATA
django_politico_slackchat_renderer-0.2.14.dist-info/RECORD
django_politico_slackchat_renderer-0.2.14.dist-info/WHEEL
django_politico_slackchat_renderer-0.2.14.dist-info/metadata.json
django_politico_slackchat_renderer-0.2.14.dist-info/top_level.txt
